pyboolector.cpython-311-x86_64-linux-gnu.so
pyboolector.libs/libboolector-c97b0552.so
pyboolector-3.2.4.19342042739.dist-info/METADATA
pyboolector-3.2.4.19342042739.dist-info/WHEEL
pyboolector-3.2.4.19342042739.dist-info/top_level.txt
pyboolector-3.2.4.19342042739.dist-info/RECORD
pyboolector-3.2.4.19342042739.dist-info/licenses/LICENSE
